ptcn/__init__.py
ptcn/components.py
ptcn/constants.py
ptcn/factories.py
ptcn/networks.py
ptcn-0.1.3.dist-info/WHEEL
ptcn-0.1.3.dist-info/METADATA
ptcn-0.1.3.dist-info/RECORD
