Metadata-Version: 2.1
Name: ptcn
Version: 0.1.3
Summary: TF2 implementation of a Temporal Convolutional Network with a probabilistic twist
Home-page: https://github.com/UpstatePedro/ptcn
License: GPL-3.0-only
Author: UpstatePedro
Requires-Python: >=3.6,<4.0
Classifier: License :: OSI Approved :: GNU General Public License v3 (GPLv3)
Classifier: Programming Language :: Python :: 3
Classifier: Programming Language :: Python :: 3.6
Classifier: Programming Language :: Python :: 3.7
Classifier: Programming Language :: Python :: 3.8
Requires-Dist: tensorflow (>=2.2.0,<3.0.0)
Requires-Dist: tensorflow-addons (>=0.10.0,<0.11.0)
Project-URL: Repository, https://github.com/UpstatePedro/ptcn
